is_codes/__init__.py
is_codes/text_reader.py
is_codes/data/my_code.py
is_codes-0.1.dist-info/METADATA
is_codes-0.1.dist-info/WHEEL
is_codes-0.1.dist-info/top_level.txt
is_codes-0.1.dist-info/RECORD
