Metadata-Version: 2.1
Name: is-codes
Version: 0.1
Summary: All IS Codes
Home-page: https://github.com/savioratharv/prac_testing
Author: davinci003
Author-email: freegpt00@gmail.com
